roast/__init__.py
roast/_static_version.py
roast/_version.py
roast/confParser.py
roast/exceptions.py
roast/serial.py
roast/ssh.py
roast/xexpect.py
roast/component/relay.py
roast/component/scenario.py
roast/component/system.py
roast/component/testsuite.py
roast/component/board/board.py
roast/providers/choices.py
roast/providers/randomizer.py
roast/providers/shuffle.py
roast/utils/__init__.py
roast/utils/file.py
roast/utils/logger.py
roast/utils/plugin.py
roast/utils/roast_utils.py
roast/utils/test_utils.py
roast-5.0.0.dist-info/AUTHORS.rst
roast-5.0.0.dist-info/LICENSE
roast-5.0.0.dist-info/METADATA
roast-5.0.0.dist-info/WHEEL
roast-5.0.0.dist-info/top_level.txt
roast-5.0.0.dist-info/RECORD
