Metadata-Version: 2.1
Name: roast
Version: 5.0.0
Summary: Randomized Okaying Across System Topologies (ROAST) Python Framework
Home-page: https://github.com/Xilinx/roast
Author: Ching-Hwa Yu
Author-email: chinghwa@xilinx.com
License: MIT
Keywords: roast
Platform: UNKNOWN
Classifier: Development Status :: 5 - Production/Stable
Classifier: Operating System :: POSIX :: Linux
Classifier: Programming Language :: Python :: 3.6
Classifier: Programming Language :: Python :: 3.7
Classifier: Programming Language :: Python :: 3.8
Classifier: Programming Language :: Python :: 3.9
Classifier: License :: OSI Approved :: MIT License
Requires-Python: >=3.6, <4
License-File: LICENSE
License-File: AUTHORS.rst
Requires-Dist: python-configuration[toml,yaml] (==0.8.2)
Requires-Dist: stevedore (>=3.0)
Requires-Dist: gitpython
Requires-Dist: pexpect
Requires-Dist: pyyaml
Requires-Dist: mimesis
Requires-Dist: filelock
Requires-Dist: python-box
Requires-Dist: plusminus
Requires-Dist: numpy
Requires-Dist: importlib-metadata (<5.0.0)
Provides-Extra: dev
Requires-Dist: pytest ; extra == 'dev'
Requires-Dist: pytest-mock ; extra == 'dev'
Requires-Dist: pytest-black ; extra == 'dev'
Requires-Dist: pytest-freezegun ; extra == 'dev'
Requires-Dist: miniver ; extra == 'dev'
Requires-Dist: coverage ; extra == 'dev'
